MANIFEST.in
README.rst
setup.cfg
setup.py
otek/__init__.py
otek/cli.py
otek/template.py