Metadata-Version: 1.1
Name: otek
Version: 0.1.9
Summary: An unopinionated project builder for everyone.
Home-page: https://github.com/jaywunder/otek
Author: Jacob Wunder
Author-email: public@jacobwunder.com
License: MIT
Keywords: project builder cli tool
Platform: UNKNOWN
Classifier: Intended Audience :: Developers
Classifier: Topic :: Utilities
Classifier: License :: OSI Approved :: MIT License
Classifier: Natural Language :: English
Classifier: Operating System :: OS Independent
Classifier: Programming Language :: Python :: 3.5
